MANIFEST.in
README.rst
setup.py
datetimecake/__init__.py
datetimecake.egg-info/PKG-INFO
datetimecake.egg-info/SOURCES.txt
datetimecake.egg-info/dependency_links.txt
datetimecake.egg-info/top_level.txt
datetimecake/cake/__init__.py
datetimecake/cake/cake.py