Metadata-Version: 1.0
Name: datetimecake
Version: 1.0.0
Summary: This is datetimecake
Home-page: UNKNOWN
Author: Mr.zhu
Author-email: mr.zhuqipeng@gmail.com
License: UNKNOWN
Platform: UNKNOWN
